[{"dep": "01", "valeur": 1.6815}, {"dep": "02", "valeur": 1.7805}, {"dep": "03", "valeur": 1.739}, {"dep": "04", "valeur": 1.699}, {"dep": "05", "valeur": 1.669}, {"dep": "06", "valeur": 1.822}, {"dep": "07", "valeur": 1.709}, {"dep": "08", "valeur": 1.789}, {"dep": "09", "valeur": 1.7225000000000001}, {"dep": "10", "valeur": 1.799}, {"dep": "11", "valeur": 1.709}, {"dep": "12", "valeur": 1.697}, {"dep": "13", "valeur": 1.673}, {"dep": "14", "valeur": 1.789}, {"dep": "15", "valeur": 1.779}, {"dep": "16", "valeur": 1.764}, {"dep": "17", "valeur": 1.7645}, {"dep": "18", "valeur": 1.7985}, {"dep": "19", "valeur": 1.788}, {"dep": "21", "valeur": 1.74}, {"dep": "22", "valeur": 1.749}, {"dep": "23", "valeur": 1.798}, {"dep": "24", "valeur": 1.759}, {"dep": "25", "valeur": 1.782}, {"dep": "26", "valeur": 1.749}, {"dep": "27", "valeur": 1.77}, {"dep": "28", "valeur": 1.7879999999999998}, {"dep": "29", "valeur": 1.7400000000000002}, {"dep": "30", "valeur": 1.762}, {"dep": "31", "valeur": 1.679}, {"dep": "32", "valeur": 1.772}, {"dep": "33", "valeur": 1.76}, {"dep": "34", "valeur": 1.709}, {"dep": "35", "valeur": 1.759}, {"dep": "36", "valeur": 1.8}, {"dep": "37", "valeur": 1.789}, {"dep": "38", "valeur": 1.703}, {"dep": "39", "valeur": 1.76}, {"dep": "40", "valeur": 1.789}, {"dep": "41", "valeur": 1.849}, {"dep": "42", "valeur": 1.699}, {"dep": "43", "valeur": 1.6925}, {"dep": "44", "valeur": 1.744}, {"dep": "45", "valeur": 1.8025}, {"dep": "46", "valeur": 1.73}, {"dep": "47", "valeur": 1.771}, {"dep": "48", "valeur": 2.04}, {"dep": "49", "valeur": 1.7654999999999998}, {"dep": "50", "valeur": 1.7894999999999999}, {"dep": "51", "valeur": 1.791}, {"dep": "52", "valeur": 1.8085}, {"dep": "53", "valeur": 1.785}, {"dep": "54", "valeur": 1.779}, {"dep": "55", "valeur": 1.809}, {"dep": "56", "valeur": 1.749}, {"dep": "57", "valeur": 1.798}, {"dep": "58", "valeur": 1.857}, {"dep": "59", "valeur": 1.779}, {"dep": "60", "valeur": 1.8}, {"dep": "61", "valeur": 1.759}, {"dep": "62", "valeur": 1.789}, {"dep": "63", "valeur": 1.699}, {"dep": "64", "valeur": 1.759}, {"dep": "65", "valeur": 1.76}, {"dep": "66", "valeur": 1.699}, {"dep": "67", "valeur": 1.772}, {"dep": "68", "valeur": 1.789}, {"dep": "69", "valeur": 1.703}, {"dep": "70", "valeur": 1.819}, {"dep": "71", "valeur": 1.781}, {"dep": "72", "valeur": 1.7894999999999999}, {"dep": "73", "valeur": 1.8035}, {"dep": "74", "valeur": 1.702}, {"dep": "75", "valeur": 1.8895}, {"dep": "76", "valeur": 1.769}, {"dep": "77", "valeur": 1.819}, {"dep": "78", "valeur": 1.8635000000000002}, {"dep": "79", "valeur": 1.765}, {"dep": "80", "valeur": 1.79}, {"dep": "81", "valeur": 1.6895}, {"dep": "82", "valeur": 1.787}, {"dep": "83", "valeur": 1.749}, {"dep": "84", "valeur": 1.686}, {"dep": "85", "valeur": 1.739}, {"dep": "86", "valeur": 1.789}, {"dep": "87", "valeur": 1.772}, {"dep": "88", "valeur": 1.7494999999999998}, {"dep": "89", "valeur": 1.899}, {"dep": "90", "valeur": 1.818}, {"dep": "91", "valeur": 1.8105}, {"dep": "92", "valeur": 2.099}, {"dep": "93", "valeur": 1.9015}, {"dep": "94", "valeur": 1.924}, {"dep": "95", "valeur": 1.827}]